{
  "current": [
    {
      "event": 1,
      "points": 49,
      "total_points": 49,
      "rank": 7015949,
      "rank_sort": 7067361,
      "overall_rank": 7015949,
      "percentile_rank": null,
      "bank": 5,
      "value": 1000,
      "event_transfers": 0,
      "event_transfers_cost": 0,
      "points_on_bench": 7
    },
    {
      "event": 2,
      "points": 27,
      "total_points": 76,
      "rank": 8484460,
      "rank_sort": 8503275,
      "overall_rank": 7424296,
      "percentile_rank": null,
      "bank": 5,
      "value": 1000,
      "event_transfers": 0,
      "event_transfers_cost": 0,
      "points_on_bench": 6
    },
    {
      "event": 3,
      "points": 39,
      "total_points": 115,
      "rank": 6224865,
      "rank_sort": 6262785,
      "overall_rank": 7310605,
      "percentile_rank": null,
      "bank": 5,
      "value": 999,
      "event_transfers": 2,
      "event_transfers_cost": 0,
      "points_on_bench": 6
    },
    {
      "event": 4,
      "points": 75,
      "total_points": 190,
      "rank": 4060550,
      "rank_sort": 4150124,
      "overall_rank": 6831306,
      "percentile_rank": null,
      "bank": 9,
      "value": 999,
      "event_transfers": 1,
      "event_transfers_cost": 0,
      "points_on_bench": 2
    },
    {
      "event": 5,
      "points": 41,
      "total_points": 231,
      "rank": 6379443,
      "rank_sort": 6450712,
      "overall_rank": 6930953,
      "percentile_rank": null,
      "bank": 17,
      "value": 999,
      "event_transfers": 1,
      "event_transfers_cost": 0,
      "points_on_bench": 3
    },
    {
      "event": 6,
      "points": 47,
      "total_points": 278,
      "rank": 9216227,
      "rank_sort": 9225422,
      "overall_rank": 7585719,
      "percentile_rank": null,
      "bank": 16,
      "value": 999,
      "event_transfers": 1,
      "event_transfers_cost": 0,
      "points_on_bench": 1
    },
    {
      "event": 7,
      "points": 33,
      "total_points": 311,
      "rank": 8755811,
      "rank_sort": 8780709,
      "overall_rank": 7967089,
      "percentile_rank": null,
      "bank": 2,
      "value": 998,
      "event_transfers": 1,
      "event_transfers_cost": 0,
      "points_on_bench": 9
    },
    {
      "event": 8,
      "points": 55,
      "total_points": 366,
      "rank": 1851156,
      "rank_sort": 1877310,
      "overall_rank": 7546176,
      "percentile_rank": null,
      "bank": 7,
      "value": 1002,
      "event_transfers": 1,
      "event_transfers_cost": 0,
      "points_on_bench": 0
    },
    {
      "event": 9,
      "points": 92,
      "total_points": 458,
      "rank": 698053,
      "rank_sort": 714873,
      "overall_rank": 6334796,
      "percentile_rank": null,
      "bank": 4,
      "value": 1003,
      "event_transfers": 1,
      "event_transfers_cost": 0,
      "points_on_bench": 2
    },
    {
      "event": 10,
      "points": 103,
      "total_points": 561,
      "rank": 17289,
      "rank_sort": 17702,
      "overall_rank": 4316830,
      "percentile_rank": null,
      "bank": 1,
      "value": 1005,
      "event_transfers": 1,
      "event_transfers_cost": 0,
      "points_on_bench": 5
    },
    {
      "event": 11,
      "points": 20,
      "total_points": 581,
      "rank": 9406996,
      "rank_sort": 9442942,
      "overall_rank": 5019221,
      "percentile_rank": null,
      "bank": 17,
      "value": 1010,
      "event_transfers": 1,
      "event_transfers_cost": 0,
      "points_on_bench": 3
    },
    {
      "event": 12,
      "points": 75,
      "total_points": 656,
      "rank": 2191128,
      "rank_sort": 2232969,
      "overall_rank": 4374603,
      "percentile_rank": null,
      "bank": 1,
      "value": 1015,
      "event_transfers": 0,
      "event_transfers_cost": 0,
      "points_on_bench": 4
    },
    {
      "event": 13,
      "points": 50,
      "total_points": 706,
      "rank": 3481538,
      "rank_sort": 3534932,
      "overall_rank": 4171082,
      "percentile_rank": null,
      "bank": 5,
      "value": 1016,
      "event_transfers": 1,
      "event_transfers_cost": 0,
      "points_on_bench": 11
    },
    {
      "event": 14,
      "points": 49,
      "total_points": 755,
      "rank": 7295600,
      "rank_sort": 7328572,
      "overall_rank": 4527935,
      "percentile_rank": null,
      "bank": 12,
      "value": 1018,
      "event_transfers": 1,
      "event_transfers_cost": 0,
      "points_on_bench": 1
    },
    {
      "event": 15,
      "points": 38,
      "total_points": 793,
      "rank": 3473488,
      "rank_sort": 3577644,
      "overall_rank": 4375423,
      "percentile_rank": null,
      "bank": 12,
      "value": 1018,
      "event_transfers": 0,
      "event_transfers_cost": 0,
      "points_on_bench": 0
    },
    {
      "event": 16,
      "points": 35,
      "total_points": 828,
      "rank": 6416833,
      "rank_sort": 6430414,
      "overall_rank": 4623178,
      "percentile_rank": null,
      "bank": 20,
      "value": 1015,
      "event_transfers": 2,
      "event_transfers_cost": 0,
      "points_on_bench": 1
    },
    {
      "event": 17,
      "points": 47,
      "total_points": 875,
      "rank": 4573385,
      "rank_sort": 4602589,
      "overall_rank": 4477310,
      "percentile_rank": null,
      "bank": 10,
      "value": 1014,
      "event_transfers": 1,
      "event_transfers_cost": 0,
      "points_on_bench": 2
    },
    {
      "event": 18,
      "points": 28,
      "total_points": 903,
      "rank": 7719054,
      "rank_sort": 7735705,
      "overall_rank": 4844141,
      "percentile_rank": null,
      "bank": 21,
      "value": 1012,
      "event_transfers": 1,
      "event_transfers_cost": 0,
      "points_on_bench": 8
    },
    {
      "event": 19,
      "points": 56,
      "total_points": 959,
      "rank": 506426,
      "rank_sort": 519403,
      "overall_rank": 4161386,
      "percentile_rank": null,
      "bank": 5,
      "value": 1012,
      "event_transfers": 1,
      "event_transfers_cost": 0,
      "points_on_bench": 10
    },
    {
      "event": 20,
      "points": 69,
      "total_points": 1028,
      "rank": 3618755,
      "rank_sort": 3644855,
      "overall_rank": 3947140,
      "percentile_rank": null,
      "bank": 6,
      "value": 1007,
      "event_transfers": 1,
      "event_transfers_cost": 0,
      "points_on_bench": 8
    },
    {
      "event": 21,
      "points": 39,
      "total_points": 1067,
      "rank": 7354400,
      "rank_sort": 7368694,
      "overall_rank": 4179851,
      "percentile_rank": 70,
      "bank": 5,
      "value": 1011,
      "event_transfers": 1,
      "event_transfers_cost": 0,
      "points_on_bench": 6
    },
    {
      "event": 22,
      "points": 35,
      "total_points": 1102,
      "rank": 8557686,
      "rank_sort": 8606303,
      "overall_rank": 4639421,
      "percentile_rank": 90,
      "bank": 5,
      "value": 1010,
      "event_transfers": 0,
      "event_transfers_cost": 0,
      "points_on_bench": 2
    },
    {
      "event": 23,
      "points": 34,
      "total_points": 1136,
      "rank": 9527742,
      "rank_sort": 9530396,
      "overall_rank": 5264078,
      "percentile_rank": 95,
      "bank": 1,
      "value": 1009,
      "event_transfers": 1,
      "event_transfers_cost": 0,
      "points_on_bench": 2
    },
    {
      "event": 24,
      "points": 59,
      "total_points": 1195,
      "rank": 6377118,
      "rank_sort": 6437094,
      "overall_rank": 5358324,
      "percentile_rank": 65,
      "bank": 1,
      "value": 1008,
      "event_transfers": 0,
      "event_transfers_cost": 0,
      "points_on_bench": 0
    },
    {
      "event": 25,
      "points": 95,
      "total_points": 1290,
      "rank": 612030,
      "rank_sort": 626875,
      "overall_rank": 4813377,
      "percentile_rank": 10,
      "bank": 1,
      "value": 1011,
      "event_transfers": 0,
      "event_transfers_cost": 0,
      "points_on_bench": 4
    },
    {
      "event": 26,
      "points": 40,
      "total_points": 1330,
      "rank": 6948926,
      "rank_sort": 6966466,
      "overall_rank": 4970630,
      "percentile_rank": 70,
      "bank": 3,
      "value": 1015,
      "event_transfers": 2,
      "event_transfers_cost": 0,
      "points_on_bench": 0
    },
    {
      "event": 27,
      "points": 72,
      "total_points": 1402,
      "rank": 2964481,
      "rank_sort": 3019137,
      "overall_rank": 4781579,
      "percentile_rank": 30,
      "bank": 3,
      "value": 1019,
      "event_transfers": 0,
      "event_transfers_cost": 0,
      "points_on_bench": 2
    },
    {
      "event": 28,
      "points": 26,
      "total_points": 1428,
      "rank": 9827184,
      "rank_sort": 9864408,
      "overall_rank": 5139342,
      "percentile_rank": 95,
      "bank": 3,
      "value": 1019,
      "event_transfers": 0,
      "event_transfers_cost": 0,
      "points_on_bench": 10
    },
    {
      "event": 29,
      "points": 14,
      "total_points": 1442,
      "rank": 3734413,
      "rank_sort": 3835678,
      "overall_rank": 5079187,
      "percentile_rank": 35,
      "bank": 3,
      "value": 1017,
      "event_transfers": 0,
      "event_transfers_cost": 0,
      "points_on_bench": 0
    },
    {
      "event": 30,
      "points": 40,
      "total_points": 1482,
      "rank": 7158031,
      "rank_sort": 7226044,
      "overall_rank": 5197473,
      "percentile_rank": 70,
      "bank": 3,
      "value": 1016,
      "event_transfers": 0,
      "event_transfers_cost": 0,
      "points_on_bench": 7
    },
    {
      "event": 31,
      "points": 43,
      "total_points": 1525,
      "rank": 5752570,
      "rank_sort": 5807330,
      "overall_rank": 5218966,
      "percentile_rank": 55,
      "bank": 3,
      "value": 1016,
      "event_transfers": 0,
      "event_transfers_cost": 0,
      "points_on_bench": 0
    },
    {
      "event": 32,
      "points": 54,
      "total_points": 1579,
      "rank": 6006201,
      "rank_sort": 6092598,
      "overall_rank": 5286077,
      "percentile_rank": 60,
      "bank": 3,
      "value": 1014,
      "event_transfers": 0,
      "event_transfers_cost": 0,
      "points_on_bench": 8
    },
    {
      "event": 33,
      "points": 43,
      "total_points": 1622,
      "rank": 8229473,
      "rank_sort": 8276883,
      "overall_rank": 5499039,
      "percentile_rank": 80,
      "bank": 3,
      "value": 1018,
      "event_transfers": 0,
      "event_transfers_cost": 0,
      "points_on_bench": 6
    },
    {
      "event": 34,
      "points": 88,
      "total_points": 1710,
      "rank": 3341967,
      "rank_sort": 3371789,
      "overall_rank": 5314950,
      "percentile_rank": 35,
      "bank": 3,
      "value": 1019,
      "event_transfers": 0,
      "event_transfers_cost": 0,
      "points_on_bench": 8
    },
    {
      "event": 35,
      "points": 61,
      "total_points": 1771,
      "rank": 2991649,
      "rank_sort": 3038864,
      "overall_rank": 5168011,
      "percentile_rank": 30,
      "bank": 3,
      "value": 1019,
      "event_transfers": 0,
      "event_transfers_cost": 0,
      "points_on_bench": 8
    },
    {
      "event": 36,
      "points": 67,
      "total_points": 1838,
      "rank": 6520889,
      "rank_sort": 6583067,
      "overall_rank": 5205227,
      "percentile_rank": 65,
      "bank": 3,
      "value": 1020,
      "event_transfers": 0,
      "event_transfers_cost": 0,
      "points_on_bench": 18
    },
    {
      "event": 37,
      "points": 75,
      "total_points": 1913,
      "rank": 6287244,
      "rank_sort": 6337218,
      "overall_rank": 5238439,
      "percentile_rank": 60,
      "bank": 3,
      "value": 1019,
      "event_transfers": 0,
      "event_transfers_cost": 0,
      "points_on_bench": 18
    },
    {
      "event": 38,
      "points": 39,
      "total_points": 1952,
      "rank": 8034091,
      "rank_sort": 8092238,
      "overall_rank": 5367313,
      "percentile_rank": 75,
      "bank": 3,
      "value": 1018,
      "event_transfers": 0,
      "event_transfers_cost": 0,
      "points_on_bench": 12
    }
  ],
  "past": [
    {
      "season_name": "2023/24",
      "total_points": 1952,
      "rank": 5367313
    }
  ],
  "chips": [
    {
      "name": "3xc",
      "time": "2023-08-07T12:00:41.076124Z",
      "event": 1
    },
    {
      "name": "wildcard",
      "time": "2023-11-07T00:59:46.374103Z",
      "event": 12
    },
    {
      "name": "freehit",
      "time": "2024-01-28T15:05:50.051387Z",
      "event": 22
    }
  ]
}