{
  "current": [
    {
      "event": 1,
      "points": 73,
      "total_points": 73,
      "rank": 2126260,
      "rank_sort": 2288730,
      "overall_rank": 2126260,
      "percentile_rank": null,
      "bank": 0,
      "value": 1000,
      "event_transfers": 0,
      "event_transfers_cost": 0,
      "points_on_bench": 6
    },
    {
      "event": 2,
      "points": 59,
      "total_points": 132,
      "rank": 979108,
      "rank_sort": 1016904,
      "overall_rank": 812849,
      "percentile_rank": null,
      "bank": 0,
      "value": 1002,
      "event_transfers": 1,
      "event_transfers_cost": 0,
      "points_on_bench": 6
    },
    {
      "event": 3,
      "points": 42,
      "total_points": 174,
      "rank": 5075485,
      "rank_sort": 5138372,
      "overall_rank": 1387198,
      "percentile_rank": null,
      "bank": 9,
      "value": 1000,
      "event_transfers": 1,
      "event_transfers_cost": 0,
      "points_on_bench": 8
    },
    {
      "event": 4,
      "points": 77,
      "total_points": 251,
      "rank": 3310650,
      "rank_sort": 3392002,
      "overall_rank": 1277283,
      "percentile_rank": null,
      "bank": 7,
      "value": 1003,
      "event_transfers": 1,
      "event_transfers_cost": 0,
      "points_on_bench": 9
    },
    {
      "event": 5,
      "points": 49,
      "total_points": 300,
      "rank": 2794044,
      "rank_sort": 2872481,
      "overall_rank": 951639,
      "percentile_rank": null,
      "bank": 7,
      "value": 1001,
      "event_transfers": 0,
      "event_transfers_cost": 0,
      "points_on_bench": 7
    },
    {
      "event": 6,
      "points": 100,
      "total_points": 396,
      "rank": 99916,
      "rank_sort": 100314,
      "overall_rank": 204108,
      "percentile_rank": null,
      "bank": 4,
      "value": 1001,
      "event_transfers": 3,
      "event_transfers_cost": 4,
      "points_on_bench": 20
    },
    {
      "event": 7,
      "points": 52,
      "total_points": 448,
      "rank": 3768955,
      "rank_sort": 3815470,
      "overall_rank": 280104,
      "percentile_rank": null,
      "bank": 4,
      "value": 1004,
      "event_transfers": 0,
      "event_transfers_cost": 0,
      "points_on_bench": 17
    },
    {
      "event": 8,
      "points": 65,
      "total_points": 509,
      "rank": 555930,
      "rank_sort": 558914,
      "overall_rank": 114884,
      "percentile_rank": null,
      "bank": 51,
      "value": 1005,
      "event_transfers": 3,
      "event_transfers_cost": 4,
      "points_on_bench": 1
    },
    {
      "event": 9,
      "points": 110,
      "total_points": 619,
      "rank": 25062,
      "rank_sort": 26039,
      "overall_rank": 15273,
      "percentile_rank": null,
      "bank": 19,
      "value": 1011,
      "event_transfers": 1,
      "event_transfers_cost": 0,
      "points_on_bench": 6
    },
    {
      "event": 10,
      "points": 42,
      "total_points": 661,
      "rank": 9856714,
      "rank_sort": 9859844,
      "overall_rank": 117065,
      "percentile_rank": null,
      "bank": 14,
      "value": 1014,
      "event_transfers": 1,
      "event_transfers_cost": 0,
      "points_on_bench": 24
    },
    {
      "event": 11,
      "points": 38,
      "total_points": 699,
      "rank": 2311526,
      "rank_sort": 2387009,
      "overall_rank": 69420,
      "percentile_rank": null,
      "bank": 14,
      "value": 1020,
      "event_transfers": 0,
      "event_transfers_cost": 0,
      "points_on_bench": 13
    },
    {
      "event": 12,
      "points": 62,
      "total_points": 761,
      "rank": 6103420,
      "rank_sort": 6129897,
      "overall_rank": 169228,
      "percentile_rank": null,
      "bank": 6,
      "value": 1020,
      "event_transfers": 2,
      "event_transfers_cost": 0,
      "points_on_bench": 10
    },
    {
      "event": 13,
      "points": 42,
      "total_points": 803,
      "rank": 6832696,
      "rank_sort": 6893412,
      "overall_rank": 244196,
      "percentile_rank": null,
      "bank": 6,
      "value": 1025,
      "event_transfers": 1,
      "event_transfers_cost": 0,
      "points_on_bench": 6
    },
    {
      "event": 14,
      "points": 70,
      "total_points": 873,
      "rank": 802441,
      "rank_sort": 836308,
      "overall_rank": 153037,
      "percentile_rank": null,
      "bank": 6,
      "value": 1024,
      "event_transfers": 0,
      "event_transfers_cost": 0,
      "points_on_bench": 7
    },
    {
      "event": 15,
      "points": 39,
      "total_points": 908,
      "rank": 3456217,
      "rank_sort": 3461684,
      "overall_rank": 160340,
      "percentile_rank": null,
      "bank": 3,
      "value": 1022,
      "event_transfers": 3,
      "event_transfers_cost": 4,
      "points_on_bench": 6
    },
    {
      "event": 16,
      "points": 66,
      "total_points": 974,
      "rank": 439082,
      "rank_sort": 456462,
      "overall_rank": 75644,
      "percentile_rank": null,
      "bank": 3,
      "value": 1023,
      "event_transfers": 0,
      "event_transfers_cost": 0,
      "points_on_bench": 4
    },
    {
      "event": 17,
      "points": 56,
      "total_points": 1030,
      "rank": 2315909,
      "rank_sort": 2350159,
      "overall_rank": 86696,
      "percentile_rank": null,
      "bank": 12,
      "value": 1024,
      "event_transfers": 2,
      "event_transfers_cost": 0,
      "points_on_bench": 2
    },
    {
      "event": 18,
      "points": 35,
      "total_points": 1065,
      "rank": 5363529,
      "rank_sort": 5442224,
      "overall_rank": 156111,
      "percentile_rank": null,
      "bank": 12,
      "value": 1029,
      "event_transfers": 0,
      "event_transfers_cost": 0,
      "points_on_bench": 9
    },
    {
      "event": 19,
      "points": 56,
      "total_points": 1121,
      "rank": 527148,
      "rank_sort": 534968,
      "overall_rank": 82722,
      "percentile_rank": null,
      "bank": 1,
      "value": 1032,
      "event_transfers": 2,
      "event_transfers_cost": 0,
      "points_on_bench": 11
    },
    {
      "event": 20,
      "points": 78,
      "total_points": 1199,
      "rank": 1988727,
      "rank_sort": 2018597,
      "overall_rank": 109213,
      "percentile_rank": null,
      "bank": 2,
      "value": 1037,
      "event_transfers": 1,
      "event_transfers_cost": 0,
      "points_on_bench": 11
    },
    {
      "event": 21,
      "points": 46,
      "total_points": 1245,
      "rank": 5263656,
      "rank_sort": 5324654,
      "overall_rank": 190862,
      "percentile_rank": 55,
      "bank": 64,
      "value": 1029,
      "event_transfers": 0,
      "event_transfers_cost": 0,
      "points_on_bench": 10
    },
    {
      "event": 22,
      "points": 63,
      "total_points": 1308,
      "rank": 1758933,
      "rank_sort": 1802938,
      "overall_rank": 158659,
      "percentile_rank": 20,
      "bank": 64,
      "value": 1031,
      "event_transfers": 0,
      "event_transfers_cost": 0,
      "points_on_bench": 13
    },
    {
      "event": 23,
      "points": 69,
      "total_points": 1377,
      "rank": 2885521,
      "rank_sort": 2901883,
      "overall_rank": 185354,
      "percentile_rank": 30,
      "bank": 57,
      "value": 1028,
      "event_transfers": 2,
      "event_transfers_cost": 0,
      "points_on_bench": 16
    },
    {
      "event": 24,
      "points": 57,
      "total_points": 1434,
      "rank": 6902140,
      "rank_sort": 6963835,
      "overall_rank": 290587,
      "percentile_rank": 70,
      "bank": 57,
      "value": 1028,
      "event_transfers": 0,
      "event_transfers_cost": 0,
      "points_on_bench": 13
    },
    {
      "event": 25,
      "points": 83,
      "total_points": 1517,
      "rank": 2727524,
      "rank_sort": 2756380,
      "overall_rank": 286051,
      "percentile_rank": 30,
      "bank": 34,
      "value": 1024,
      "event_transfers": 2,
      "event_transfers_cost": 0,
      "points_on_bench": 0
    },
    {
      "event": 26,
      "points": 74,
      "total_points": 1591,
      "rank": 361482,
      "rank_sort": 374865,
      "overall_rank": 173389,
      "percentile_rank": 5,
      "bank": 34,
      "value": 1026,
      "event_transfers": 0,
      "event_transfers_cost": 0,
      "points_on_bench": 3
    },
    {
      "event": 27,
      "points": 87,
      "total_points": 1678,
      "rank": 536583,
      "rank_sort": 548214,
      "overall_rank": 132339,
      "percentile_rank": 10,
      "bank": 35,
      "value": 1026,
      "event_transfers": 2,
      "event_transfers_cost": 0,
      "points_on_bench": 18
    },
    {
      "event": 28,
      "points": 46,
      "total_points": 1720,
      "rank": 4807819,
      "rank_sort": 4834217,
      "overall_rank": 190402,
      "percentile_rank": 45,
      "bank": 70,
      "value": 1032,
      "event_transfers": 2,
      "event_transfers_cost": 4,
      "points_on_bench": 8
    },
    {
      "event": 29,
      "points": 21,
      "total_points": 1741,
      "rank": 1398967,
      "rank_sort": 1519230,
      "overall_rank": 176127,
      "percentile_rank": 15,
      "bank": 70,
      "value": 1033,
      "event_transfers": 0,
      "event_transfers_cost": 0,
      "points_on_bench": 20
    },
    {
      "event": 30,
      "points": 35,
      "total_points": 1776,
      "rank": 8318526,
      "rank_sort": 8382064,
      "overall_rank": 304098,
      "percentile_rank": 80,
      "bank": 70,
      "value": 1030,
      "event_transfers": 0,
      "event_transfers_cost": 0,
      "points_on_bench": 13
    },
    {
      "event": 31,
      "points": 56,
      "total_points": 1832,
      "rank": 3427880,
      "rank_sort": 3445234,
      "overall_rank": 334350,
      "percentile_rank": 35,
      "bank": 3,
      "value": 1023,
      "event_transfers": 2,
      "event_transfers_cost": 0,
      "points_on_bench": 1
    },
    {
      "event": 32,
      "points": 53,
      "total_points": 1885,
      "rank": 6351174,
      "rank_sort": 6439300,
      "overall_rank": 398256,
      "percentile_rank": 60,
      "bank": 3,
      "value": 1021,
      "event_transfers": 0,
      "event_transfers_cost": 0,
      "points_on_bench": 10
    },
    {
      "event": 33,
      "points": 75,
      "total_points": 1960,
      "rank": 2191876,
      "rank_sort": 2230108,
      "overall_rank": 385397,
      "percentile_rank": 25,
      "bank": 3,
      "value": 1020,
      "event_transfers": 0,
      "event_transfers_cost": 0,
      "points_on_bench": 0
    },
    {
      "event": 34,
      "points": 139,
      "total_points": 2095,
      "rank": 127251,
      "rank_sort": 128098,
      "overall_rank": 189879,
      "percentile_rank": 5,
      "bank": 11,
      "value": 1020,
      "event_transfers": 3,
      "event_transfers_cost": 4,
      "points_on_bench": 3
    },
    {
      "event": 35,
      "points": 41,
      "total_points": 2132,
      "rank": 8299505,
      "rank_sort": 8303950,
      "overall_rank": 334325,
      "percentile_rank": 80,
      "bank": 14,
      "value": 1021,
      "event_transfers": 2,
      "event_transfers_cost": 4,
      "points_on_bench": 11
    },
    {
      "event": 36,
      "points": 74,
      "total_points": 2206,
      "rank": 5078891,
      "rank_sort": 5095285,
      "overall_rank": 411310,
      "percentile_rank": 50,
      "bank": 37,
      "value": 1018,
      "event_transfers": 1,
      "event_transfers_cost": 0,
      "points_on_bench": 24
    },
    {
      "event": 37,
      "points": 101,
      "total_points": 2295,
      "rank": 2820120,
      "rank_sort": 2822806,
      "overall_rank": 564616,
      "percentile_rank": 30,
      "bank": 6,
      "value": 1011,
      "event_transfers": 4,
      "event_transfers_cost": 12,
      "points_on_bench": 23
    },
    {
      "event": 38,
      "points": 56,
      "total_points": 2351,
      "rank": 4584879,
      "rank_sort": 4611255,
      "overall_rank": 634203,
      "percentile_rank": 45,
      "bank": 4,
      "value": 1014,
      "event_transfers": 1,
      "event_transfers_cost": 0,
      "points_on_bench": 41
    }
  ],
  "past": [
    {
      "season_name": "2022/23",
      "total_points": 1893,
      "rank": 6523980
    },
    {
      "season_name": "2023/24",
      "total_points": 2351,
      "rank": 634203
    }
  ],
  "chips": [
    {
      "name": "wildcard",
      "time": "2024-01-12T09:52:49.427648Z",
      "event": 21
    },
    {
      "name": "bboost",
      "time": "2024-02-15T10:27:29.659156Z",
      "event": 25
    },
    {
      "name": "freehit",
      "time": "2024-03-16T07:10:17.502392Z",
      "event": 29
    },
    {
      "name": "3xc",
      "time": "2024-04-20T00:10:01.003714Z",
      "event": 34
    }
  ]
}