{
  "current": [
    {
      "event": 1,
      "points": 86,
      "total_points": 86,
      "rank": 170883,
      "rank_sort": 175207,
      "overall_rank": 170883,
      "percentile_rank": null,
      "bank": 0,
      "value": 1000,
      "event_transfers": 0,
      "event_transfers_cost": 0,
      "points_on_bench": 23
    },
    {
      "event": 2,
      "points": 45,
      "total_points": 131,
      "rank": 4360019,
      "rank_sort": 4369782,
      "overall_rank": 903660,
      "percentile_rank": null,
      "bank": 10,
      "value": 1002,
      "event_transfers": 1,
      "event_transfers_cost": 0,
      "points_on_bench": 5
    },
    {
      "event": 3,
      "points": 59,
      "total_points": 190,
      "rank": 856019,
      "rank_sort": 860106,
      "overall_rank": 301690,
      "percentile_rank": null,
      "bank": 9,
      "value": 1007,
      "event_transfers": 1,
      "event_transfers_cost": 0,
      "points_on_bench": 4
    },
    {
      "event": 4,
      "points": 71,
      "total_points": 261,
      "rank": 5541804,
      "rank_sort": 5546741,
      "overall_rank": 565417,
      "percentile_rank": null,
      "bank": 9,
      "value": 1009,
      "event_transfers": 0,
      "event_transfers_cost": 0,
      "points_on_bench": 1
    },
    {
      "event": 5,
      "points": 46,
      "total_points": 307,
      "rank": 4183830,
      "rank_sort": 4191933,
      "overall_rank": 547310,
      "percentile_rank": null,
      "bank": 7,
      "value": 1008,
      "event_transfers": 1,
      "event_transfers_cost": 0,
      "points_on_bench": 4
    },
    {
      "event": 6,
      "points": 102,
      "total_points": 409,
      "rank": 62535,
      "rank_sort": 62736,
      "overall_rank": 54197,
      "percentile_rank": null,
      "bank": 0,
      "value": 1011,
      "event_transfers": 2,
      "event_transfers_cost": 0,
      "points_on_bench": 0
    },
    {
      "event": 7,
      "points": 56,
      "total_points": 461,
      "rank": 2996054,
      "rank_sort": 2999341,
      "overall_rank": 104641,
      "percentile_rank": null,
      "bank": 2,
      "value": 1013,
      "event_transfers": 2,
      "event_transfers_cost": 4,
      "points_on_bench": 0
    },
    {
      "event": 8,
      "points": 32,
      "total_points": 493,
      "rank": 8789962,
      "rank_sort": 8792512,
      "overall_rank": 349258,
      "percentile_rank": null,
      "bank": 6,
      "value": 1015,
      "event_transfers": 1,
      "event_transfers_cost": 0,
      "points_on_bench": 0
    },
    {
      "event": 9,
      "points": 86,
      "total_points": 579,
      "rank": 1408299,
      "rank_sort": 1413196,
      "overall_rank": 266885,
      "percentile_rank": null,
      "bank": 8,
      "value": 1016,
      "event_transfers": 1,
      "event_transfers_cost": 0,
      "points_on_bench": 3
    },
    {
      "event": 10,
      "points": 74,
      "total_points": 653,
      "rank": 2640608,
      "rank_sort": 2647309,
      "overall_rank": 191137,
      "percentile_rank": null,
      "bank": 0,
      "value": 1011,
      "event_transfers": 0,
      "event_transfers_cost": 0,
      "points_on_bench": 4
    },
    {
      "event": 11,
      "points": 36,
      "total_points": 689,
      "rank": 2990395,
      "rank_sort": 2997507,
      "overall_rank": 132795,
      "percentile_rank": null,
      "bank": 0,
      "value": 1019,
      "event_transfers": 0,
      "event_transfers_cost": 0,
      "points_on_bench": 12
    },
    {
      "event": 12,
      "points": 87,
      "total_points": 776,
      "rank": 490567,
      "rank_sort": 493632,
      "overall_rank": 65056,
      "percentile_rank": null,
      "bank": 3,
      "value": 1024,
      "event_transfers": 1,
      "event_transfers_cost": 0,
      "points_on_bench": 4
    },
    {
      "event": 13,
      "points": 54,
      "total_points": 830,
      "rank": 2147976,
      "rank_sort": 2154491,
      "overall_rank": 47660,
      "percentile_rank": null,
      "bank": 5,
      "value": 1029,
      "event_transfers": 1,
      "event_transfers_cost": 0,
      "points_on_bench": 1
    },
    {
      "event": 14,
      "points": 67,
      "total_points": 897,
      "rank": 1490904,
      "rank_sort": 1495298,
      "overall_rank": 35410,
      "percentile_rank": null,
      "bank": 4,
      "value": 1030,
      "event_transfers": 2,
      "event_transfers_cost": 0,
      "points_on_bench": 4
    },
    {
      "event": 15,
      "points": 35,
      "total_points": 932,
      "rank": 5123626,
      "rank_sort": 5137650,
      "overall_rank": 37688,
      "percentile_rank": null,
      "bank": 4,
      "value": 1031,
      "event_transfers": 1,
      "event_transfers_cost": 0,
      "points_on_bench": 8
    },
    {
      "event": 16,
      "points": 58,
      "total_points": 990,
      "rank": 1496744,
      "rank_sort": 1502722,
      "overall_rank": 27750,
      "percentile_rank": null,
      "bank": 14,
      "value": 1032,
      "event_transfers": 1,
      "event_transfers_cost": 0,
      "points_on_bench": 3
    },
    {
      "event": 17,
      "points": 70,
      "total_points": 1056,
      "rank": 363057,
      "rank_sort": 367316,
      "overall_rank": 18688,
      "percentile_rank": null,
      "bank": 75,
      "value": 1036,
      "event_transfers": 2,
      "event_transfers_cost": 4,
      "points_on_bench": 1
    },
    {
      "event": 18,
      "points": 48,
      "total_points": 1104,
      "rank": 2035285,
      "rank_sort": 2039396,
      "overall_rank": 19025,
      "percentile_rank": null,
      "bank": 75,
      "value": 1042,
      "event_transfers": 0,
      "event_transfers_cost": 0,
      "points_on_bench": 32
    },
    {
      "event": 19,
      "points": 43,
      "total_points": 1147,
      "rank": 3278519,
      "rank_sort": 3289185,
      "overall_rank": 19183,
      "percentile_rank": null,
      "bank": 37,
      "value": 1048,
      "event_transfers": 1,
      "event_transfers_cost": 0,
      "points_on_bench": 12
    },
    {
      "event": 20,
      "points": 87,
      "total_points": 1234,
      "rank": 827499,
      "rank_sort": 832802,
      "overall_rank": 17574,
      "percentile_rank": null,
      "bank": 13,
      "value": 1051,
      "event_transfers": 1,
      "event_transfers_cost": 0,
      "points_on_bench": 14
    },
    {
      "event": 21,
      "points": 68,
      "total_points": 1302,
      "rank": 999598,
      "rank_sort": 1001333,
      "overall_rank": 12984,
      "percentile_rank": 10,
      "bank": 38,
      "value": 1051,
      "event_transfers": 1,
      "event_transfers_cost": 0,
      "points_on_bench": 3
    },
    {
      "event": 22,
      "points": 73,
      "total_points": 1375,
      "rank": 459606,
      "rank_sort": 462509,
      "overall_rank": 5637,
      "percentile_rank": 5,
      "bank": 87,
      "value": 1051,
      "event_transfers": 1,
      "event_transfers_cost": 0,
      "points_on_bench": 6
    },
    {
      "event": 23,
      "points": 81,
      "total_points": 1456,
      "rank": 1132494,
      "rank_sort": 1136409,
      "overall_rank": 4231,
      "percentile_rank": 15,
      "bank": 16,
      "value": 1050,
      "event_transfers": 1,
      "event_transfers_cost": 0,
      "points_on_bench": 22
    },
    {
      "event": 24,
      "points": 93,
      "total_points": 1549,
      "rank": 122966,
      "rank_sort": 123743,
      "overall_rank": 1508,
      "percentile_rank": 5,
      "bank": 11,
      "value": 1054,
      "event_transfers": 1,
      "event_transfers_cost": 0,
      "points_on_bench": 4
    },
    {
      "event": 25,
      "points": 94,
      "total_points": 1643,
      "rank": 753687,
      "rank_sort": 755997,
      "overall_rank": 1246,
      "percentile_rank": 10,
      "bank": 45,
      "value": 1053,
      "event_transfers": 1,
      "event_transfers_cost": 0,
      "points_on_bench": 5
    },
    {
      "event": 26,
      "points": 57,
      "total_points": 1700,
      "rank": 2561810,
      "rank_sort": 2566620,
      "overall_rank": 1433,
      "percentile_rank": 25,
      "bank": 51,
      "value": 1055,
      "event_transfers": 1,
      "event_transfers_cost": 0,
      "points_on_bench": 0
    },
    {
      "event": 27,
      "points": 82,
      "total_points": 1782,
      "rank": 1089349,
      "rank_sort": 1096177,
      "overall_rank": 1283,
      "percentile_rank": 15,
      "bank": 16,
      "value": 1061,
      "event_transfers": 1,
      "event_transfers_cost": 0,
      "points_on_bench": 14
    },
    {
      "event": 28,
      "points": 66,
      "total_points": 1848,
      "rank": 729963,
      "rank_sort": 733648,
      "overall_rank": 888,
      "percentile_rank": 10,
      "bank": 109,
      "value": 1062,
      "event_transfers": 2,
      "event_transfers_cost": 0,
      "points_on_bench": 10
    },
    {
      "event": 29,
      "points": 17,
      "total_points": 1861,
      "rank": 2829336,
      "rank_sort": 2834499,
      "overall_rank": 1312,
      "percentile_rank": 30,
      "bank": 105,
      "value": 1058,
      "event_transfers": 2,
      "event_transfers_cost": 4,
      "points_on_bench": 0
    },
    {
      "event": 30,
      "points": 75,
      "total_points": 1936,
      "rank": 189229,
      "rank_sort": 190951,
      "overall_rank": 638,
      "percentile_rank": 5,
      "bank": 15,
      "value": 1053,
      "event_transfers": 0,
      "event_transfers_cost": 0,
      "points_on_bench": 16
    },
    {
      "event": 31,
      "points": 49,
      "total_points": 1985,
      "rank": 4545061,
      "rank_sort": 4549424,
      "overall_rank": 1511,
      "percentile_rank": 45,
      "bank": 15,
      "value": 1060,
      "event_transfers": 0,
      "event_transfers_cost": 0,
      "points_on_bench": 16
    },
    {
      "event": 32,
      "points": 58,
      "total_points": 2043,
      "rank": 4849235,
      "rank_sort": 4855497,
      "overall_rank": 2335,
      "percentile_rank": 50,
      "bank": 9,
      "value": 1065,
      "event_transfers": 1,
      "event_transfers_cost": 0,
      "points_on_bench": 10
    },
    {
      "event": 33,
      "points": 112,
      "total_points": 2155,
      "rank": 29972,
      "rank_sort": 30033,
      "overall_rank": 271,
      "percentile_rank": 1,
      "bank": 14,
      "value": 1066,
      "event_transfers": 2,
      "event_transfers_cost": 0,
      "points_on_bench": 12
    },
    {
      "event": 34,
      "points": 135,
      "total_points": 2290,
      "rank": 166893,
      "rank_sort": 167942,
      "overall_rank": 86,
      "percentile_rank": 5,
      "bank": 14,
      "value": 1069,
      "event_transfers": 0,
      "event_transfers_cost": 0,
      "points_on_bench": 28
    },
    {
      "event": 35,
      "points": 95,
      "total_points": 2385,
      "rank": 30708,
      "rank_sort": 30797,
      "overall_rank": 35,
      "percentile_rank": 1,
      "bank": 63,
      "value": 1069,
      "event_transfers": 1,
      "event_transfers_cost": 0,
      "points_on_bench": 7
    },
    {
      "event": 36,
      "points": 109,
      "total_points": 2494,
      "rank": 162773,
      "rank_sort": 164033,
      "overall_rank": 29,
      "percentile_rank": 5,
      "bank": 63,
      "value": 1074,
      "event_transfers": 0,
      "event_transfers_cost": 0,
      "points_on_bench": 2
    },
    {
      "event": 37,
      "points": 144,
      "total_points": 2638,
      "rank": 90259,
      "rank_sort": 91547,
      "overall_rank": 16,
      "percentile_rank": 1,
      "bank": 21,
      "value": 1081,
      "event_transfers": 2,
      "event_transfers_cost": 0,
      "points_on_bench": 0
    },
    {
      "event": 38,
      "points": 70,
      "total_points": 2708,
      "rank": 1971038,
      "rank_sort": 1976264,
      "overall_rank": 20,
      "percentile_rank": 20,
      "bank": 17,
      "value": 1084,
      "event_transfers": 1,
      "event_transfers_cost": 0,
      "points_on_bench": 7
    }
  ],
  "past": [
    {
      "season_name": "2007/08",
      "total_points": 1879,
      "rank": 393045
    },
    {
      "season_name": "2008/09",
      "total_points": 1782,
      "rank": 311682
    },
    {
      "season_name": "2009/10",
      "total_points": 2098,
      "rank": 211487
    },
    {
      "season_name": "2010/11",
      "total_points": 2079,
      "rank": 19931
    },
    {
      "season_name": "2011/12",
      "total_points": 2100,
      "rank": 41586
    },
    {
      "season_name": "2012/13",
      "total_points": 2209,
      "rank": 10822
    },
    {
      "season_name": "2013/14",
      "total_points": 2292,
      "rank": 91787
    },
    {
      "season_name": "2014/15",
      "total_points": 2177,
      "rank": 14538
    },
    {
      "season_name": "2015/16",
      "total_points": 2241,
      "rank": 16030
    },
    {
      "season_name": "2016/17",
      "total_points": 2202,
      "rank": 65541
    },
    {
      "season_name": "2017/18",
      "total_points": 2232,
      "rank": 70255
    },
    {
      "season_name": "2018/19",
      "total_points": 2339,
      "rank": 27889
    },
    {
      "season_name": "2019/20",
      "total_points": 2279,
      "rank": 77640
    },
    {
      "season_name": "2020/21",
      "total_points": 2339,
      "rank": 224527
    },
    {
      "season_name": "2021/22",
      "total_points": 2490,
      "rank": 120831
    },
    {
      "season_name": "2022/23",
      "total_points": 2579,
      "rank": 25521
    },
    {
      "season_name": "2023/24",
      "total_points": 2708,
      "rank": 20
    }
  ],
  "chips": [
    {
      "name": "wildcard",
      "time": "2023-10-21T22:26:17.659433Z",
      "event": 10
    },
    {
      "name": "3xc",
      "time": "2024-02-15T20:45:37.326211Z",
      "event": 25
    },
    {
      "name": "wildcard",
      "time": "2024-03-17T19:53:12.782398Z",
      "event": 30
    },
    {
      "name": "freehit",
      "time": "2024-04-13T11:30:33.960756Z",
      "event": 34
    },
    {
      "name": "bboost",
      "time": "2024-05-03T18:15:33.291183Z",
      "event": 37
    }
  ]
}