{
  "id": 699645,
  "joined_time": "2023-07-06T14:06:39.002422Z",
  "started_event": 1,
  "favourite_team": 14,
  "player_first_name": "Charin",
  "player_last_name": "Iamprapakul",
  "player_region_id": 212,
  "player_region_name": "Thailand",
  "player_region_iso_code_short": "TH",
  "player_region_iso_code_long": "THA",
  "years_active": 13,
  "summary_overall_points": 2702,
  "summary_overall_rank": 23,
  "summary_event_points": 71,
  "summary_event_rank": 1826993,
  "current_event": 38,
  "leagues": {
    "classic": [
      {
        "id": 14,
        "name": "Man Utd",
        "short_name": "team-14",
        "created": "2023-07-05T15:13:48.844577Z",
        "closed": false,
        "rank": null,
        "max_entries": null,
        "league_type": "s",
        "scoring": "c",
        "admin_entry": null,
        "start_event": 1,
        "entry_can_leave": false,
        "entry_can_admin": false,
        "entry_can_invite": false,
        "has_cup": true,
        "cup_league": 2350458,
        "cup_qualified": true,
        "rank_count": 2352261,
        "entry_percentile_rank": 1,
        "entry_rank": 1,
        "entry_last_rank": 2
      },
      {
        "id": 232,
        "name": "Thailand",
        "short_name": "region-212",
        "created": "2023-07-05T15:13:53.098333Z",
        "closed": false,
        "rank": null,
        "max_entries": null,
        "league_type": "s",
        "scoring": "c",
        "admin_entry": null,
        "start_event": 1,
        "entry_can_leave": false,
        "entry_can_admin": false,
        "entry_can_invite": false,
        "has_cup": true,
        "cup_league": 2394593,
        "cup_qualified": true,
        "rank_count": 77733,
        "entry_percentile_rank": 1,
        "entry_rank": 1,
        "entry_last_rank": 1
      },
      {
        "id": 276,
        "name": "Gameweek 1",
        "short_name": "event-1",
        "created": "2023-07-05T15:13:53.946163Z",
        "closed": false,
        "rank": null,
        "max_entries": null,
        "league_type": "s",
        "scoring": "c",
        "admin_entry": null,
        "start_event": 1,
        "entry_can_leave": false,
        "entry_can_admin": false,
        "entry_can_invite": false,
        "has_cup": false,
        "cup_league": null,
        "cup_qualified": null,
        "rank_count": 8015130,
        "entry_percentile_rank": 1,
        "entry_rank": 23,
        "entry_last_rank": 29
      },
      {
        "id": 314,
        "name": "Overall",
        "short_name": "overall",
        "created": "2023-07-05T15:13:54.679154Z",
        "closed": false,
        "rank": null,
        "max_entries": null,
        "league_type": "s",
        "scoring": "c",
        "admin_entry": null,
        "start_event": 1,
        "entry_can_leave": false,
        "entry_can_admin": false,
        "entry_can_invite": false,
        "has_cup": true,
        "cup_league": 2337883,
        "cup_qualified": true,
        "rank_count": 10838474,
        "entry_percentile_rank": 1,
        "entry_rank": 23,
        "entry_last_rank": 29
      },
      {
        "id": 316,
        "name": "Second Chance",
        "short_name": "sc",
        "created": "2023-07-05T15:13:54.716611Z",
        "closed": false,
        "rank": null,
        "max_entries": null,
        "league_type": "s",
        "scoring": "c",
        "admin_entry": null,
        "start_event": 21,
        "entry_can_leave": false,
        "entry_can_admin": false,
        "entry_can_invite": false,
        "has_cup": false,
        "cup_league": null,
        "cup_qualified": null,
        "rank_count": 10838464,
        "entry_percentile_rank": 1,
        "entry_rank": 137,
        "entry_last_rank": 145
      },
      {
        "id": 316718,
        "name": "FPL สามเซียน 23/24",
        "short_name": null,
        "created": "2023-07-12T09:04:23.339266Z",
        "closed": false,
        "rank": null,
        "max_entries": null,
        "league_type": "x",
        "scoring": "c",
        "admin_entry": 5934,
        "start_event": 21,
        "entry_can_leave": false,
        "entry_can_admin": false,
        "entry_can_invite": false,
        "has_cup": true,
        "cup_league": 2419152,
        "cup_qualified": true,
        "rank_count": 2392,
        "entry_percentile_rank": 1,
        "entry_rank": 3,
        "entry_last_rank": 5
      },
      {
        "id": 346716,
        "name": "SCG_All Stars",
        "short_name": null,
        "created": "2023-07-13T17:37:22.227601Z",
        "closed": false,
        "rank": null,
        "max_entries": null,
        "league_type": "x",
        "scoring": "c",
        "admin_entry": 1767145,
        "start_event": 1,
        "entry_can_leave": false,
        "entry_can_admin": false,
        "entry_can_invite": false,
        "has_cup": true,
        "cup_league": 2663774,
        "cup_qualified": true,
        "rank_count": 13,
        "entry_percentile_rank": 10,
        "entry_rank": 1,
        "entry_last_rank": 1
      },
      {
        "id": 571627,
        "name": "TFC - Thai FPL Club",
        "short_name": null,
        "created": "2023-07-26T00:39:26.232055Z",
        "closed": true,
        "rank": null,
        "max_entries": null,
        "league_type": "x",
        "scoring": "c",
        "admin_entry": 50806,
        "start_event": 1,
        "entry_can_leave": false,
        "entry_can_admin": false,
        "entry_can_invite": false,
        "has_cup": true,
        "cup_league": 2419244,
        "cup_qualified": true,
        "rank_count": 2128,
        "entry_percentile_rank": 1,
        "entry_rank": 1,
        "entry_last_rank": 1
      },
      {
        "id": 690638,
        "name": "FPL Thai Bros Season 5",
        "short_name": null,
        "created": "2023-07-31T12:10:23.202128Z",
        "closed": true,
        "rank": null,
        "max_entries": null,
        "league_type": "x",
        "scoring": "c",
        "admin_entry": 302212,
        "start_event": 1,
        "entry_can_leave": false,
        "entry_can_admin": false,
        "entry_can_invite": false,
        "has_cup": true,
        "cup_league": 2424280,
        "cup_qualified": true,
        "rank_count": 1433,
        "entry_percentile_rank": 1,
        "entry_rank": 1,
        "entry_last_rank": 1
      },
      {
        "id": 751796,
        "name": "FPL DEEP–TALKS SEASON 2",
        "short_name": null,
        "created": "2023-08-02T04:40:25.460561Z",
        "closed": true,
        "rank": null,
        "max_entries": null,
        "league_type": "x",
        "scoring": "c",
        "admin_entry": 2486,
        "start_event": 1,
        "entry_can_leave": false,
        "entry_can_admin": false,
        "entry_can_invite": false,
        "has_cup": true,
        "cup_league": 2429624,
        "cup_qualified": true,
        "rank_count": 582,
        "entry_percentile_rank": 1,
        "entry_rank": 1,
        "entry_last_rank": 1
      },
      {
        "id": 754260,
        "name": "Rich Man Party",
        "short_name": null,
        "created": "2023-08-02T07:08:25.236580Z",
        "closed": false,
        "rank": null,
        "max_entries": null,
        "league_type": "x",
        "scoring": "c",
        "admin_entry": 699645,
        "start_event": 1,
        "entry_can_leave": false,
        "entry_can_admin": true,
        "entry_can_invite": true,
        "has_cup": true,
        "cup_league": 2603064,
        "cup_qualified": true,
        "rank_count": 19,
        "entry_percentile_rank": 10,
        "entry_rank": 1,
        "entry_last_rank": 1
      },
      {
        "id": 827314,
        "name": "True Visions League",
        "short_name": "brd-truevisions",
        "created": "2023-08-03T15:23:59.213005Z",
        "closed": false,
        "rank": null,
        "max_entries": null,
        "league_type": "s",
        "scoring": "c",
        "admin_entry": null,
        "start_event": 1,
        "entry_can_leave": false,
        "entry_can_admin": false,
        "entry_can_invite": false,
        "has_cup": true,
        "cup_league": 2394606,
        "cup_qualified": true,
        "rank_count": 77733,
        "entry_percentile_rank": 1,
        "entry_rank": 1,
        "entry_last_rank": 1
      }
    ],
    "h2h": [],
    "cup": {
      "matches": [],
      "status": {
        "qualification_event": null,
        "qualification_numbers": null,
        "qualification_rank": null,
        "qualification_state": null
      },
      "cup_league": null
    },
    "cup_matches": [
      {
        "id": 89775550,
        "entry_1_entry": 699645,
        "entry_1_name": "ฺBoyCharinFC",
        "entry_1_player_name": "Charin Iamprapakul",
        "entry_1_points": 57,
        "entry_1_win": 0,
        "entry_1_draw": 0,
        "entry_1_loss": 0,
        "entry_1_total": 0,
        "entry_2_entry": 347871,
        "entry_2_name": "Red Devils fc",
        "entry_2_player_name": "ryan winter",
        "entry_2_points": 65,
        "entry_2_win": 0,
        "entry_2_draw": 0,
        "entry_2_loss": 0,
        "entry_2_total": 0,
        "is_knockout": true,
        "league": 2350458,
        "winner": 347871,
        "seed_value": null,
        "event": 19,
        "tiebreak": null,
        "is_bye": false,
        "knockout_name": "Round of 1048576"
      },
      {
        "id": 114165412,
        "entry_1_entry": 383815,
        "entry_1_name": "Sergio Georgini",
        "entry_1_player_name": "Fartein Behrentz Færevaag",
        "entry_1_points": 78,
        "entry_1_win": 0,
        "entry_1_draw": 0,
        "entry_1_loss": 0,
        "entry_1_total": 0,
        "entry_2_entry": 699645,
        "entry_2_name": "ฺBoyCharinFC",
        "entry_2_player_name": "Charin Iamprapakul",
        "entry_2_points": 75,
        "entry_2_win": 0,
        "entry_2_draw": 0,
        "entry_2_loss": 0,
        "entry_2_total": 0,
        "is_knockout": true,
        "league": 2337883,
        "winner": 383815,
        "seed_value": null,
        "event": 24,
        "tiebreak": null,
        "is_bye": false,
        "knockout_name": "Round of 32768"
      },
      {
        "id": 122673841,
        "entry_1_entry": 513124,
        "entry_1_name": "Yasothon FC",
        "entry_1_player_name": "Jatuphot Phuatawee",
        "entry_1_points": 79,
        "entry_1_win": 0,
        "entry_1_draw": 0,
        "entry_1_loss": 0,
        "entry_1_total": 0,
        "entry_2_entry": 699645,
        "entry_2_name": "ฺBoyCharinFC",
        "entry_2_player_name": "Charin Iamprapakul",
        "entry_2_points": 79,
        "entry_2_win": 0,
        "entry_2_draw": 0,
        "entry_2_loss": 0,
        "entry_2_total": 0,
        "is_knockout": true,
        "league": 2394593,
        "winner": 513124,
        "seed_value": null,
        "event": 27,
        "tiebreak": "goals_conceded",
        "is_bye": false,
        "knockout_name": "Round of 4096"
      },
      {
        "id": 124751297,
        "entry_1_entry": 525500,
        "entry_1_name": "LiverCool",
        "entry_1_player_name": "B SoCool",
        "entry_1_points": 58,
        "entry_1_win": 0,
        "entry_1_draw": 0,
        "entry_1_loss": 0,
        "entry_1_total": 0,
        "entry_2_entry": 699645,
        "entry_2_name": "ฺBoyCharinFC",
        "entry_2_player_name": "Charin Iamprapakul",
        "entry_2_points": 53,
        "entry_2_win": 0,
        "entry_2_draw": 0,
        "entry_2_loss": 0,
        "entry_2_total": 0,
        "is_knockout": true,
        "league": 2394606,
        "winner": 525500,
        "seed_value": null,
        "event": 28,
        "tiebreak": null,
        "is_bye": false,
        "knockout_name": "Round of 2048"
      },
      {
        "id": 125453828,
        "entry_1_entry": 119513,
        "entry_1_name": "Fantasystic FC",
        "entry_1_player_name": "Shane A",
        "entry_1_points": 68,
        "entry_1_win": 0,
        "entry_1_draw": 0,
        "entry_1_loss": 0,
        "entry_1_total": 0,
        "entry_2_entry": 699645,
        "entry_2_name": "ฺBoyCharinFC",
        "entry_2_player_name": "Charin Iamprapakul",
        "entry_2_points": 53,
        "entry_2_win": 0,
        "entry_2_draw": 0,
        "entry_2_loss": 0,
        "entry_2_total": 0,
        "is_knockout": true,
        "league": 2419152,
        "winner": 119513,
        "seed_value": null,
        "event": 28,
        "tiebreak": null,
        "is_bye": false,
        "knockout_name": "Round of 2048"
      },
      {
        "id": 125548431,
        "entry_1_entry": 1498845,
        "entry_1_name": "Abdulbooks",
        "entry_1_player_name": "smanachan buddhajak",
        "entry_1_points": 70,
        "entry_1_win": 0,
        "entry_1_draw": 0,
        "entry_1_loss": 0,
        "entry_1_total": 0,
        "entry_2_entry": 699645,
        "entry_2_name": "ฺBoyCharinFC",
        "entry_2_player_name": "Charin Iamprapakul",
        "entry_2_points": 53,
        "entry_2_win": 0,
        "entry_2_draw": 0,
        "entry_2_loss": 0,
        "entry_2_total": 0,
        "is_knockout": true,
        "league": 2419244,
        "winner": 1498845,
        "seed_value": null,
        "event": 28,
        "tiebreak": null,
        "is_bye": false,
        "knockout_name": "Round of 2048"
      },
      {
        "id": 127219724,
        "entry_1_entry": 917003,
        "entry_1_name": "Edmundor FC",
        "entry_1_player_name": "Pichayuth Thongchaikul",
        "entry_1_points": 16,
        "entry_1_win": 0,
        "entry_1_draw": 0,
        "entry_1_loss": 0,
        "entry_1_total": 0,
        "entry_2_entry": 699645,
        "entry_2_name": "ฺBoyCharinFC",
        "entry_2_player_name": "Charin Iamprapakul",
        "entry_2_points": 14,
        "entry_2_win": 0,
        "entry_2_draw": 0,
        "entry_2_loss": 0,
        "entry_2_total": 0,
        "is_knockout": true,
        "league": 2424280,
        "winner": 917003,
        "seed_value": null,
        "event": 29,
        "tiebreak": null,
        "is_bye": false,
        "knockout_name": "Round of 1024"
      },
      {
        "id": 129696690,
        "entry_1_entry": 17854,
        "entry_1_name": "Lui2",
        "entry_1_player_name": "วรพัชชา บุญมี",
        "entry_1_points": 61,
        "entry_1_win": 0,
        "entry_1_draw": 0,
        "entry_1_loss": 0,
        "entry_1_total": 0,
        "entry_2_entry": 699645,
        "entry_2_name": "ฺBoyCharinFC",
        "entry_2_player_name": "Charin Iamprapakul",
        "entry_2_points": 61,
        "entry_2_win": 0,
        "entry_2_draw": 0,
        "entry_2_loss": 0,
        "entry_2_total": 0,
        "is_knockout": true,
        "league": 2429624,
        "winner": 17854,
        "seed_value": null,
        "event": 31,
        "tiebreak": "default",
        "is_bye": false,
        "knockout_name": "Round of 256"
      },
      {
        "id": 146619489,
        "entry_1_entry": 699645,
        "entry_1_name": "ฺBoyCharinFC",
        "entry_1_player_name": "Charin Iamprapakul",
        "entry_1_points": 131,
        "entry_1_win": 0,
        "entry_1_draw": 0,
        "entry_1_loss": 0,
        "entry_1_total": 0,
        "entry_2_entry": 6440972,
        "entry_2_name": "ｚｅｕｓ",
        "entry_2_player_name": "Ματθαῖος แมตตี้",
        "entry_2_points": 131,
        "entry_2_win": 0,
        "entry_2_draw": 0,
        "entry_2_loss": 0,
        "entry_2_total": 0,
        "is_knockout": true,
        "league": 2603064,
        "winner": 6440972,
        "seed_value": null,
        "event": 37,
        "tiebreak": "default",
        "is_bye": false,
        "knockout_name": "Semi-final"
      },
      {
        "id": 149518248,
        "entry_1_entry": 4220082,
        "entry_1_name": "nattaphonq",
        "entry_1_player_name": "Nattaphong Jaturunsomboon",
        "entry_1_points": 53,
        "entry_1_win": 0,
        "entry_1_draw": 0,
        "entry_1_loss": 0,
        "entry_1_total": 0,
        "entry_2_entry": 699645,
        "entry_2_name": "ฺBoyCharinFC",
        "entry_2_player_name": "Charin Iamprapakul",
        "entry_2_points": 71,
        "entry_2_win": 0,
        "entry_2_draw": 0,
        "entry_2_loss": 0,
        "entry_2_total": 0,
        "is_knockout": true,
        "league": 2663774,
        "winner": 699645,
        "seed_value": null,
        "event": 38,
        "tiebreak": null,
        "is_bye": false,
        "knockout_name": "Final"
      }
    ]
  },
  "name": "ฺBoyCharinFC",
  "name_change_blocked": false,
  "entered_events": [
    1,
    2,
    3,
    4,
    5,
    6,
    7,
    8,
    9,
    10,
    11,
    12,
    13,
    14,
    15,
    16,
    17,
    18,
    19,
    20,
    21,
    22,
    23,
    24,
    25,
    26,
    27,
    28,
    29,
    30,
    31,
    32,
    33,
    34,
    35,
    36,
    37,
    38
  ],
  "kit": null,
  "last_deadline_bank": 19,
  "last_deadline_value": 1063,
  "last_deadline_total_transfers": 40
}